miniapp/__init__.py
miniapp/errs.py
miniapp/api/__init__.py
miniapp/api/auth.py
miniapp/api/base.py
miniapp/api/capture_user_activity.py
miniapp/api/cat_base.py
miniapp/api/cat_common.py
miniapp/api/cat_help.py
miniapp/api/cat_mem_leaks.py
miniapp/api/cat_user.py
miniapp/api/cat_user_activity.py
miniapp/api/client.py
miniapp/api/configbase.py
miniapp/api/decorators.py
miniapp/api/entrypoint.py
miniapp/api/misc_endpoints.py
miniapp/api/sso_utils.py
miniapp/comm/__init__.py
miniapp/comm/binding.py
miniapp/comm/coerce.py
miniapp/comm/csrf.py
miniapp/comm/http.py
miniapp/comm/proxy.py
miniapp/comm/request.py
miniapp/comm/rest.py
miniapp/comm/session.py
miniapp/comm/session_activity.py
miniapp/comm/swagger.py
miniapp/comm/utils.py
miniapp/data/__init__.py
miniapp/data/const.py
miniapp/data/db.py
miniapp/data/db_cache.py
miniapp/data/db_disk.py
miniapp/data/db_lock.py
miniapp/data/impl.py
miniapp/data/query_db.py
miniapp/utils/__init__.py
miniapp/utils/cmdline.py
miniapp/utils/file_utils.py
miniapp/utils/generic_obj.py
miniapp/utils/job_mgr.py
miniapp/utils/json_utils.py
miniapp/utils/lru_cache.py
miniapp/utils/message_queue.py
miniapp/utils/misc.py
miniapp/utils/reloader.py
miniapp/utils/schedule_utils.py
miniapp/utils/smtp_emailer.py
miniapp/utils/task_runner.py
miniapp/utils/template_utils.py
miniapp/utils/timeline_utils.py
miniapp-0.1.1.dist-info/METADATA
miniapp-0.1.1.dist-info/WHEEL
miniapp-0.1.1.dist-info/top_level.txt
miniapp-0.1.1.dist-info/RECORD
