Metadata-Version: 2.1
Name: miniapp
Version: 0.1.1
Summary: Microservice Base
Home-page: UNKNOWN
License: Apache
Platform: UNKNOWN
Classifier: License :: OSI Approved :: Apache Software License
Classifier: Programming Language :: Python :: 3
Requires-Dist: jsonschema
Provides-Extra: all
Requires-Dist: pytz ; extra == 'all'
Requires-Dist: jinja2 ; extra == 'all'
